{
"type": "FeatureCollection",
"name": "geo_06_地域密着型特定施設入居者生活介護（有料老人ホーム（サービス付き高齢者向け住宅））",
"crs": { "type": "name", "properties": { "name": "urn:ogc:def:crs:OGC:1.3:CRS84" } },
"features": [
{ "type": "Feature", "properties": { "内容": "サービス付き高齢者向け住宅小白川【地域密着型特定施設入居者生活介護（有料老人ホーム（サービス付き高齢者向け住宅））】山形県山形市小白川町二丁目3番1号　小白川ケアセンター内", "url": "https://www.kaigokensaku.mhlw.go.jp/06/index.php?action_kouhyou_detail_004_kani=true&JigyosyoCd=0690100862-00&ServiceCd=&Type=search", "url2": "https://yamagata-saiseikai.org/" }, "geometry": { "type": "Point", "coordinates": [ 140.3503809, 38.2496233 ] } }
]
}
